f1_report/__init__.py
f1_report/cli.py
f1_report/log_reader.py
f1_report/main.py
f1_report/print_report.py
f1_report/report_builder.py
tests/__init__.py
tests/test_cli.py
f1_report-1.0.0.dist-info/LICENSE.txt
f1_report-1.0.0.dist-info/METADATA
f1_report-1.0.0.dist-info/WHEEL
f1_report-1.0.0.dist-info/top_level.txt
f1_report-1.0.0.dist-info/RECORD
